_sounddevice.py
sounddevice.py
sounddevice-0.5.0.dist-info/LICENSE
sounddevice-0.5.0.dist-info/METADATA
sounddevice-0.5.0.dist-info/WHEEL
sounddevice-0.5.0.dist-info/top_level.txt
sounddevice-0.5.0.dist-info/zip-safe
sounddevice-0.5.0.dist-info/RECORD
